{
  "eventType": "attr_set",
  "specVersion": 5,
  "eventData": {
    "changes": [
      {
        "key": "$eve.type",
        "value": "session"
      },
      {
        "key": "$eve.trigger",
        "value": "http"
      },
      {
        "key": "$eve.title",
        "value": "hello again"
      }
    ],
    "writer": {
      "type": "step",
      "stepId": "step_01KVXCAG4ZF6JYKGRA9PDN0T6W",
      "attempt": 1
    },
    "allowReservedAttributes": true
  },
  "runId": "wrun_01KVXCAG4ZKSK8X782CB83G7PV",
  "eventId": "evnt_01KVXCAG5DJ2YNQC7S2ZEXWZWQ",
  "createdAt": "2026-06-24T17:54:51.693Z"
}